{
    "type": "object",
    "description": "Create new selection",
    "required": [
        "name",
        "operation",
        "details"
    ],
    "properties": {
        "name": {
            "$ref": "#/definitions/TaskName"
        },
        "operation": {
            "type": "string",
            "enum": [
                "selection.create"
            ]
        },
        "skip": {
            "type": "boolean"
        },
        "filter": {
            "type": "string"
        },
        "details": {
            "oneOf": [
                {
                    "type": "object",
                    "required": [
                        "type"
                    ],
                    "properties": {
                        "type": {
                            "type": "string",
                            "enum": [
                                "app",
                                "app/content",
                                "app/datasegment",
                                "app/internal",
                                "app/object",
                                "appcontentquota",
                                "appseedinfo",
                                "appstatus",
                                "binarydelete",
                                "binarydownload",
                                "binarysyncruleevaluation",
                                "compositeevent",
                                "compositeeventoperational",
                                "compositeeventruleoperational",
                                "contentcachecontrol",
                                "contentlibrary",
                                "custombannermessage",
                                "custompropertydefinition",
                                "dataconnection",
                                "engineservice",
                                "executionresult",
                                "executionresult/detail",
                                "executionsession",
                                "extension",
                                "externalproductsignon",
                                "externalprogramtask",
                                "externalprogramtaskoperational",
                                "fileextension",
                                "fileextensionwhitelist",
                                "filereference",
                                "license/analyzeraccessgroup",
                                "license/analyzeraccesstype",
                                "license/analyzeraccessusage",
                                "license/analyzertimeaccesstype",
                                "license/analyzertimeaccessusage",
                                "license/loginaccesstype",
                                "license/loginaccessusage",
                                "license/professionalaccessgroup",
                                "license/professionalaccesstype",
                                "license/professionalaccessusage",
                                "license/useraccessgroup",
                                "license/useraccesstype",
                                "license/useraccessusage",
                                "lock",
                                "many",
                                "mimetype",
                                "odagenginegroup",
                                "odaglink",
                                "odaglinkusage",
                                "odagmodelgroup",
                                "odagrequest",
                                "odagservice",
                                "previewcreateprivilege",
                                "previewprivileges",
                                "printingservice",
                                "proxyservice",
                                "proxyservicecertificate",
                                "reloadtask",
                                "reloadtaskoperational",
                                "repositoryservice",
                                "schedulerservice",
                                "schemaevent",
                                "schemaeventoperational",
                                "servernodeconfiguration",
                                "servernodeheartbeat",
                                "servernoderole",
                                "servicecluster",
                                "servicestatus",
                                "sharedcontent",
                                "staticcontentreference",
                                "stream",
                                "syncsession",
                                "systeminfo",
                                "systemnotification",
                                "systemrule",
                                "tag",
                                "tempcontent",
                                "user",
                                "userdirectory",
                                "usersynctask",
                                "usersynctaskoperational",
                                "virtualproxyconfig"
                            ]
                        }
                    }
                },
                {
                    "type": "array",
                    "minItems": 1,
                    "items": {
                        "type": "object",
                        "properties": {
                            "objectId": {
                                "type": "string"
                            },
                            "type": {
                                "type": "string",
                                "enum": [
                                    "app",
                                    "app/content",
                                    "app/datasegment",
                                    "app/internal",
                                    "app/object",
                                    "appcontentquota",
                                    "appseedinfo",
                                    "appstatus",
                                    "binarydelete",
                                    "binarydownload",
                                    "binarysyncruleevaluation",
                                    "compositeevent",
                                    "compositeeventoperational",
                                    "compositeeventruleoperational",
                                    "contentcachecontrol",
                                    "contentlibrary",
                                    "custombannermessage",
                                    "custompropertydefinition",
                                    "dataconnection",
                                    "engineservice",
                                    "executionresult",
                                    "executionresult/detail",
                                    "executionsession",
                                    "extension",
                                    "externalproductsignon",
                                    "externalprogramtask",
                                    "externalprogramtaskoperational",
                                    "fileextension",
                                    "fileextensionwhitelist",
                                    "filereference",
                                    "license/analyzeraccessgroup",
                                    "license/analyzeraccesstype",
                                    "license/analyzeraccessusage",
                                    "license/analyzertimeaccesstype",
                                    "license/analyzertimeaccessusage",
                                    "license/loginaccesstype",
                                    "license/loginaccessusage",
                                    "license/professionalaccessgroup",
                                    "license/professionalaccesstype",
                                    "license/professionalaccessusage",
                                    "license/useraccessgroup",
                                    "license/useraccesstype",
                                    "license/useraccessusage",
                                    "lock",
                                    "many",
                                    "mimetype",
                                    "odagenginegroup",
                                    "odaglink",
                                    "odaglinkusage",
                                    "odagmodelgroup",
                                    "odagrequest",
                                    "odagservice",
                                    "previewcreateprivilege",
                                    "previewprivileges",
                                    "printingservice",
                                    "proxyservice",
                                    "proxyservicecertificate",
                                    "reloadtask",
                                    "reloadtaskoperational",
                                    "repositoryservice",
                                    "schedulerservice",
                                    "schemaevent",
                                    "schemaeventoperational",
                                    "servernodeconfiguration",
                                    "servernodeheartbeat",
                                    "servernoderole",
                                    "servicecluster",
                                    "servicestatus",
                                    "sharedcontent",
                                    "staticcontentreference",
                                    "stream",
                                    "syncsession",
                                    "systeminfo",
                                    "systemnotification",
                                    "systemrule",
                                    "tag",
                                    "tempcontent",
                                    "user",
                                    "userdirectory",
                                    "usersynctask",
                                    "usersynctaskoperational",
                                    "virtualproxyconfig"
                                ]
                            }
                        }
                    }
                }
            ]
        }
    }
}